{
  "blocks": [
    {
      "id": "3exte5Rg",
      "type": "tcmsleftDrawerConfig",
      "data": {
        "menuItems": [
          {
            "icon": "mdi-cart",
            "label": "Advantages",
            "link": "/advantages"
          },
          {
            "icon": "mdi-documents",
            "label": "Documentation",
            "link": "/docs"
          },
          {
            "icon": "mdi-information-variant",
            "label": "About Us",
            "link": "/about"
          },
          {
            "icon": "mdi-card-accoount-mail",
            "label": "Contact Us",
            "link": "/contact"
          },
          {
            "icon": "mdi-cart",
            "label": "Shop",
            "link": "/shop"
          },
          {
            "icon": "mdi-blog",
            "label": "Blogs",
            "link": "/blogs"
          }
        ]
      }
    }
  ]
}